LICENSE
MANIFEST.in
README.md
requirements.txt
setup.cfg
setup.py
inc/interface.h
inc/lawson_hanson.h
inc/liq_struct_data.h
inc/liquid-model.h
inc/mthread.h
inc/nash.h
inc/nepheline.h
inc/param_struct_data.h
inc/param_struct_data_CO2.h
inc/param_struct_data_CO2_H2O.h
inc/param_struct_data_v34.h
inc/recipes.h
inc/silmin.h
inc/sol_struct_data.h
inc/status.h
src/albite.c
src/alloy-liquid.c
src/alloy-solid.c
src/amphibole.c
src/biotite.c
src/biotiteTaj.c
src/check_coexisting_liquids.c
src/check_coexisting_solids.c
src/clinopyroxene.c
src/cummingtonite.c
src/equality_constraints.c
src/est_satState_revised.c
src/est_saturation_state.c
src/evaluate_saturation.c
src/feldspar.c
src/fluid.c
src/fluidPhase.c
src/frac.c
src/garnet.c
src/gibbs.c
src/gradient_hessian.c
src/hornblende.c
src/ilmenite.c
src/kalsilite.c
src/lawson_hanson.c
src/leucite.c
src/linear_search.c
src/liquid.c
src/liquid_CO2.c
src/liquid_CO2_H2O.c
src/liquid_v34.c
src/liquidus.c
src/majorite.c
src/melilite.c
src/melts_support.c
src/melts_threads.c
src/mthread.c
src/nash.c
src/nepheline.c
src/olivine-sx.c
src/olivine.c
src/ortho-oxide.c
src/orthopyroxene.c
src/perovskite.c
src/read_write.c
src/recipes.c
src/rhombohedral.c
src/rhomsghiorso.c
src/ringwoodite.c
src/silmin.c
src/silmin_support.c
src/spinel.c
src/subSolidusMuO2.c
src/wadsleyite.c
src/water.c
src/wustite.c
src/melts/__init__.py
src/melts/cframework.c
src/melts/cframework.h
src/melts/rMELTSframework.c
src/melts/rMELTSframework.pyx
src/melts_cython_framework.egg-info/PKG-INFO
src/melts_cython_framework.egg-info/SOURCES.txt
src/melts_cython_framework.egg-info/dependency_links.txt
src/melts_cython_framework.egg-info/not-zip-safe
src/melts_cython_framework.egg-info/requires.txt
src/melts_cython_framework.egg-info/top_level.txt