Metadata-Version: 2.1
Name: melts-cython-framework
Version: 1.1.2
Summary: Wrappers for the MELTS library exposed as a webservice
Home-page: https://gitlab.com/ENKI-portal/app-melts-for-excel-gca
Author: Mark S. Ghiorso
Author-email: ghiorso@ofm-research.org
License: GNU AGPLv3
Project-URL: Documentation, https://gitlab.com/ENKI-portal/app-melts-for-excel-gca
Project-URL: Code, https://gitlab.com/ENKI-portal/app-melts-for-excel-gca
Project-URL: Issue tracker, https://gitlab.com/ENKI-portal/app-melts-for-excel-gca
Classifier: Development Status :: 3 - Alpha
Classifier: License :: OSI Approved :: GNU Affero General Public License v3 or later (AGPLv3+)
Classifier: Intended Audience :: Developers
Classifier: Intended Audience :: Education
Classifier: Intended Audience :: Science/Research
Classifier: Topic :: Scientific/Engineering
Classifier: Topic :: Scientific/Engineering :: Chemistry
Classifier: Topic :: Scientific/Engineering :: Mathematics
Classifier: Topic :: Scientific/Engineering :: Physics
Classifier: Topic :: Software Development :: Libraries :: Python Modules
Classifier: Natural Language :: English
Classifier: Operating System :: OS Independent
Classifier: Programming Language :: C
Classifier: Programming Language :: Cython
Classifier: Programming Language :: Python
Classifier: Programming Language :: Python :: 3.6
Classifier: Programming Language :: Python :: 3.7
Classifier: Programming Language :: Python :: 3.8
Classifier: Programming Language :: Python :: 3.9
Classifier: Programming Language :: Python :: 3 :: Only
Classifier: Programming Language :: Python :: Implementation :: CPython
Requires-Python: >=3.6
License-File: LICENSE
